odoo/addons/sale_order_report_hide_discounts_by_partner/README.rst
odoo/addons/sale_order_report_hide_discounts_by_partner/__init__.py
odoo/addons/sale_order_report_hide_discounts_by_partner/__manifest__.py
odoo/addons/sale_order_report_hide_discounts_by_partner/data/data.xml
odoo/addons/sale_order_report_hide_discounts_by_partner/i18n/ca_ES.po
odoo/addons/sale_order_report_hide_discounts_by_partner/i18n/es.po
odoo/addons/sale_order_report_hide_discounts_by_partner/models/__init__.py
odoo/addons/sale_order_report_hide_discounts_by_partner/models/res_partner.py
odoo/addons/sale_order_report_hide_discounts_by_partner/models/sale_order.py
odoo/addons/sale_order_report_hide_discounts_by_partner/reports/sale_report_templates.xml
odoo/addons/sale_order_report_hide_discounts_by_partner/static/description/icon.png
odoo/addons/sale_order_report_hide_discounts_by_partner/tests/__init__.py
odoo/addons/sale_order_report_hide_discounts_by_partner/tests/test_hide_sale_discounts_by_partner.py
odoo/addons/sale_order_report_hide_discounts_by_partner/views/res_partner_views.xml
odoo/addons/sale_order_report_hide_discounts_by_partner/views/sale_order_views.xml
odoo_addon_sale_order_report_hide_discounts_by_partner-16.0.1.1.1.dist-info/METADATA
odoo_addon_sale_order_report_hide_discounts_by_partner-16.0.1.1.1.dist-info/WHEEL
odoo_addon_sale_order_report_hide_discounts_by_partner-16.0.1.1.1.dist-info/top_level.txt
odoo_addon_sale_order_report_hide_discounts_by_partner-16.0.1.1.1.dist-info/RECORD
